{
  "project_info": {
    "project_number": "201485625265",
    "project_id": "declut-a2b8f",
    "storage_bucket": "declut-a2b8f.appspot.com"
  },
  "client": [
    {
      "client_info": {
        "mobilesdk_app_id": "1:201485625265:android:a17b9d26fdaeaf80937f90",
        "android_client_info": {
          "package_name": "com.declut"
        }
      },
      "oauth_client": [],
      "api_key": [
        {
          "current_key": "AIzaSyAzlz_Rd5X3RDU-yAhOmK18BfiAGGcDPWo"
        }
      ],
      "services": {
        "appinvite_service": {
          "other_platform_oauth_client": []
        }
      }
    }
  ],
  "configuration_version": "1"
}